anki_reader/__init__.py
anki_reader/anki_api.py
anki_reader-0.0.2.dist-info/METADATA
anki_reader-0.0.2.dist-info/WHEEL
anki_reader-0.0.2.dist-info/top_level.txt
anki_reader-0.0.2.dist-info/RECORD
